MANIFEST.in
setup.py
version.py
pyyoutrack.egg-info/PKG-INFO
pyyoutrack.egg-info/SOURCES.txt
pyyoutrack.egg-info/dependency_links.txt
pyyoutrack.egg-info/requires.txt
pyyoutrack.egg-info/top_level.txt
youtrack/__init__.py
youtrack/connection.py
youtrack/importHelper.py