Metadata-Version: 1.1
Name: pyyoutrack
Version: 1.0.8
Summary: Python library that wraps YouTrack REST API.
Home-page: https://github.com/teonite/youtrack-rest-python-library
Author: Krzysztof Krzysztofik
Author-email: kkrzysztofik@teonite.com
License: Apache License, Version 2.0
Platform: UNKNOWN
Classifier: Development Status :: 4 - Beta
Classifier: License :: OSI Approved :: Apache Software License
Classifier: Programming Language :: Python :: 2.7
